kirt08_exceptions/exceptions.py
kirt08_exceptions-0.1.1.dist-info/METADATA
kirt08_exceptions-0.1.1.dist-info/WHEEL
kirt08_exceptions-0.1.1.dist-info/RECORD
