Metadata-Version: 2.4
Name: kirt08-exceptions
Version: 0.1.1
Summary: 
Author: Your Name
Author-email: you@example.com
Requires-Python: >=3.12
Classifier: Programming Language :: Python :: 3
Classifier: Programming Language :: Python :: 3.12
Classifier: Programming Language :: Python :: 3.13
Classifier: Programming Language :: Python :: 3.14
Requires-Dist: fastapi (>=0.128.0,<0.129.0)
